oapi2mockserver/__init__.py
oapi2mockserver/cli_entrypoint.py
oapi2mockserver/converter.py
oapi2mockserver/expectation.py
oapi2mockserver/open_api_schema.py
oapi2mockserver/requester.py
oapi2mockserver/scenario.py
oapi2mockserver-0.0.14.dist-info/LICENSE
oapi2mockserver-0.0.14.dist-info/METADATA
oapi2mockserver-0.0.14.dist-info/WHEEL
oapi2mockserver-0.0.14.dist-info/entry_points.txt
oapi2mockserver-0.0.14.dist-info/top_level.txt
oapi2mockserver-0.0.14.dist-info/RECORD
