Metadata-Version: 2.1
Name: oapi2mockserver
Version: 0.0.14
Summary: Provides the basic setup of an API mockserver.
Author: allmyhomes GmbH
Author-email: opensource@allmyhomes.com
Classifier: Programming Language :: Python :: 3
Classifier: License :: OSI Approved :: MIT License
Classifier: Operating System :: OS Independent
Provides: oapi2mockserver
License-File: LICENSE
Requires-Dist: flex (==6.14.1)
Requires-Dist: prance (==23.6.21.0)
Requires-Dist: requests (==2.31.0)
Requires-Dist: jsonschema (==4.18.4)
Requires-Dist: openapi-spec-validator (==0.6.0)
